LICENSE.md
MANIFEST.in
README.md
changelog.rst
requirements.txt
setup.py
rmr/__init__.py
rmr/errors.py
rmr/types.py
rmr/extensions/__init__.py
rmr/extensions/middleware/__init__.py
rmr/extensions/middleware/cache.py
rmr/extensions/middleware/json.py
rmr/extensions/middleware/version.py
rmr/forms/__init__.py
rmr/forms/fields.py
rmr/forms/offset_limit.py
rmr/forms/start_stop.py
rmr/management/__init__.py
rmr/management/commands.py
rmr/middleware/__init__.py
rmr/middleware/json.py
rmr/middleware/version.py
rmr/models/__init__.py
rmr/models/utils.py
rmr/models/fields/__init__.py
rmr/models/fields/hash_lookup.py
rmr/models/fields/pg_ltree.py
rmr/models/fields/pg_trigram.py
rmr/models/fields/range.py
rmr/utils/__init__.py
rmr/utils/cache.py
rmr/utils/datetime.py
rmr/utils/db.py
rmr/utils/decorators.py
rmr/utils/hash.py
rmr/utils/iterate.py
rmr/utils/patch.py
rmr/utils/range.py
rmr/utils/test.py
rmr/views/__init__.py
rmr/views/json.py
rmr/views/decorators/__init__.py
rmr/views/decorators/auth.py
rmr/views/decorators/validation.py
rmr_django.egg-info/PKG-INFO
rmr_django.egg-info/SOURCES.txt
rmr_django.egg-info/dependency_links.txt
rmr_django.egg-info/requires.txt
rmr_django.egg-info/top_level.txt